{
  "aliases": {
    "Los Angeles Dodgers": "Dodger Stadium",
    "New York Yankees": "Yankee Stadium",
    "San Francisco Giants": "Oracle Park",
    "Oakland Athletics": "Oakland Coliseum",
    "Tampa Bay Rays": "Tropicana Field",
    "Los Angeles Angels": "Angel Stadium of Anaheim",
    "Baltimore Orioles": "Oriole Park at Camden Yards",
    "Boston Red Sox": "Fenway Park",
    "Chicago White Sox": "Guaranteed Rate Field",
    "Cleveland Guardians": "Progressive Field",
    "Detroit Tigers": "Comerica Park",
    "Kansas City Royals": "Kauffman Stadium",
    "Minnesota Twins": "Target Field",
    "Texas Rangers": "Globe Life Field",
    "Toronto Blue Jays": "Rogers Centre",
    "Arizona Diamondbacks": "Chase Field",
    "Atlanta Braves": "Truist Park",
    "Chicago Cubs": "Wrigley Field",
    "Cincinnati Reds": "Great American Ball Park",
    "Colorado Rockies": "Coors Field",
    "Miami Marlins": "loanDepot park",
    "Houston Astros": "Minute Maid Park",
    "Milwaukee Brewers": "American Family Field",
    "Washington Nationals": "Nationals Park",
    "New York Mets": "Citi Field",
    "Philadelphia Phillies": "Citizens Bank Park",
    "Pittsburgh Pirates": "PNC Park",
    "St. Louis Cardinals": "Busch Stadium",
    "San Diego Padres": "Petco Park",
    "Angels": "Angel Stadium of Anaheim",
    "Orioles": "Oriole Park at Camden Yards",
    "Red Sox": "Fenway Park",
    "White Sox": "Guaranteed Rate Field",
    "Guardians": "Progressive Field",
    "Tigers": "Comerica Park",
    "Royals": "Kauffman Stadium",
    "Twins": "Target Field",
    "Rangers": "Globe Life Field",
    "Blue Jays": "Rogers Centre",
    "Diamondbacks": "Chase Field",
    "Braves": "Truist Park",
    "Cubs": "Wrigley Field",
    "Reds": "Great American Ball Park",
    "Rockies": "Coors Field",
    "Marlins": "loanDepot park",
    "Astros": "Minute Maid Park",
    "Brewers": "American Family Field",
    "Nationals": "Nationals Park",
    "Mets": "Citi Field",
    "Phillies": "Citizens Bank Park",
    "Pirates": "PNC Park",
    "Cardinals": "Busch Stadium",
    "Padres": "Petco Park",
    "Giants": "Oracle Park",
    "Athletics": "Oakland Coliseum",
    "Rays": "Tropicana Field",
    "Seattle Mariners": "T-Mobile Park"
  },
  "park_factor": {
    "Angel Stadium of Anaheim": 101,
    "Oriole Park at Camden Yards": 99,
    "Fenway Park": 104,
    "Guaranteed Rate Field": 100,
    "Progressive Field": 99,
    "Comerica Park": 100,
    "Kauffman Stadium": 103,
    "Target Field": 100,
    "Yankee Stadium": 99,
    "Oakland Coliseum": 103,
    "T-Mobile Park": 93,
    "Tropicana Field": 101,
    "Globe Life Field": 99,
    "Rogers Centre": 100,
    "Chase Field": 101,
    "Truist Park": 100,
    "Wrigley Field": 97,
    "Great American Ball Park": 105,
    "Coors Field": 113,
    "loanDepot park": 101,
    "Minute Maid Park": 100,
    "Dodger Stadium": 99,
    "American Family Field": 98,
    "Nationals Park": 100,
    "Citi Field": 96,
    "Citizens Bank Park": 102,
    "PNC Park": 101,
    "Busch Stadium": 98,
    "Petco Park": 96,
    "Oracle Park": 97
  }
}